<annotation>
	<folder>database</folder>
	<filename>000122.jpg</filename>
	<path>G:\database\y12.jpg</path>
	<source>
		<database>Unknown</database>
	</source>
	<size>
		<width>2478</width>
		<height>2478</height>
		<depth>3</depth>
	</size>
	<segmented>0</segmented>
	<object>
		<name>Disease-C</name>
		<pose>Unspecified</pose>
		<truncated>0</truncated>
		<difficult>0</difficult>
		<bndbox>
			<xmin>1325</xmin>
			<ymin>1069</ymin>
			<xmax>1930</xmax>
			<ymax>1656</ymax>
		</bndbox>
	</object>
	<object>
		<name>Disease-C</name>
		<pose>Unspecified</pose>
		<truncated>0</truncated>
		<difficult>0</difficult>
		<bndbox>
			<xmin>960</xmin>
			<ymin>1238</ymin>
			<xmax>1346</xmax>
			<ymax>1516</ymax>
		</bndbox>
	</object>
	<object>
		<name>Disease-B</name>
		<pose>Unspecified</pose>
		<truncated>0</truncated>
		<difficult>0</difficult>
		<bndbox>
			<xmin>1136</xmin>
			<ymin>1344</ymin>
			<xmax>1295</xmax>
			<ymax>1456</ymax>
		</bndbox>
	</object>
	<object>
		<name>Disease-B</name>
		<pose>Unspecified</pose>
		<truncated>0</truncated>
		<difficult>0</difficult>
		<bndbox>
			<xmin>1309</xmin>
			<ymin>987</ymin>
			<xmax>1437</xmax>
			<ymax>1078</ymax>
		</bndbox>
	</object>
</annotation>