<annotation>
	<folder>s1</folder>
	<filename>001606.jpg</filename>
	<path>G:\s1\s4.jpg</path>
	<source>
		<database>Unknown</database>
	</source>
	<size>
		<width>2703</width>
		<height>2703</height>
		<depth>3</depth>
	</size>
	<segmented>0</segmented>
	<object>
		<name>Disease-A</name>
		<pose>Unspecified</pose>
		<truncated>0</truncated>
		<difficult>0</difficult>
		<bndbox>
			<xmin>1524</xmin>
			<ymin>1488</ymin>
			<xmax>1680</xmax>
			<ymax>1647</ymax>
		</bndbox>
	</object>
	<object>
		<name>Disease-A</name>
		<pose>Unspecified</pose>
		<truncated>0</truncated>
		<difficult>0</difficult>
		<bndbox>
			<xmin>1432</xmin>
			<ymin>1581</ymin>
			<xmax>1554</xmax>
			<ymax>1699</ymax>
		</bndbox>
	</object>
	<object>
		<name>Disease-A</name>
		<pose>Unspecified</pose>
		<truncated>0</truncated>
		<difficult>0</difficult>
		<bndbox>
			<xmin>1278</xmin>
			<ymin>1400</ymin>
			<xmax>1405</xmax>
			<ymax>1517</ymax>
		</bndbox>
	</object>
	<object>
		<name>Disease-A</name>
		<pose>Unspecified</pose>
		<truncated>0</truncated>
		<difficult>0</difficult>
		<bndbox>
			<xmin>1377</xmin>
			<ymin>1352</ymin>
			<xmax>1473</xmax>
			<ymax>1456</ymax>
		</bndbox>
	</object>
	<object>
		<name>Disease-A</name>
		<pose>Unspecified</pose>
		<truncated>0</truncated>
		<difficult>0</difficult>
		<bndbox>
			<xmin>1562</xmin>
			<ymin>987</ymin>
			<xmax>1648</xmax>
			<ymax>1075</ymax>
		</bndbox>
	</object>
	<object>
		<name>Disease-A</name>
		<pose>Unspecified</pose>
		<truncated>0</truncated>
		<difficult>0</difficult>
		<bndbox>
			<xmin>1736</xmin>
			<ymin>1527</ymin>
			<xmax>1799</xmax>
			<ymax>1591</ymax>
		</bndbox>
	</object>
</annotation>