<annotation>
	<folder></folder>
	<filename>e8199bb0e4a7edf94351ca07a5aadc06_jpg.rf.e7bcf5a47e55cfdadaf0754a0944e4d9.jpg</filename>
	<path>e8199bb0e4a7edf94351ca07a5aadc06_jpg.rf.e7bcf5a47e55cfdadaf0754a0944e4d9.jpg</path>
	<source>
		<database>roboflow.ai</database>
	</source>
	<size>
		<width>416</width>
		<height>416</height>
		<depth>3</depth>
	</size>
	<segmented>0</segmented>
	<object>
		<name>Bell_pepper leaf</name>
		<pose>Unspecified</pose>
		<truncated>0</truncated>
		<difficult>0</difficult>
		<occluded>0</occluded>
		<bndbox>
			<xmin>81</xmin>
			<xmax>326</xmax>
			<ymin>125</ymin>
			<ymax>415</ymax>
		</bndbox>
	</object>
</annotation>
